telegrambots/__init__.py
telegrambots/py.typed
telegrambots/wrapper/__init__.py
telegrambots/wrapper/api_response_exception.py
telegrambots/wrapper/client.py
telegrambots/wrapper/serializations.py
telegrambots/wrapper/_client_utilities/__init__.py
telegrambots/wrapper/_client_utilities/_client_getter.py
telegrambots/wrapper/_client_utilities/_client_setter.py
telegrambots/wrapper/_client_utilities/client_targetable.py
telegrambots/wrapper/types/__init__.py
telegrambots/wrapper/types/api_method.py
telegrambots/wrapper/types/api_multipart_method.py
telegrambots/wrapper/types/api_object.py
telegrambots/wrapper/types/api_result.py
telegrambots/wrapper/types/methods/__init__.py
telegrambots/wrapper/types/methods/add_sticker_to_set.py
telegrambots/wrapper/types/methods/answer_callback_query.py
telegrambots/wrapper/types/methods/answer_inline_query.py
telegrambots/wrapper/types/methods/answer_pre_checkout_query.py
telegrambots/wrapper/types/methods/answer_shipping_query.py
telegrambots/wrapper/types/methods/answer_web_app_query.py
telegrambots/wrapper/types/methods/approve_chat_join_request.py
telegrambots/wrapper/types/methods/ban_chat_member.py
telegrambots/wrapper/types/methods/ban_chat_sender_chat.py
telegrambots/wrapper/types/methods/close.py
telegrambots/wrapper/types/methods/copy_message.py
telegrambots/wrapper/types/methods/create_chat_invite_link.py
telegrambots/wrapper/types/methods/create_new_sticker_set.py
telegrambots/wrapper/types/methods/decline_chat_join_request.py
telegrambots/wrapper/types/methods/delete_chat_photo.py
telegrambots/wrapper/types/methods/delete_chat_sticker_set.py
telegrambots/wrapper/types/methods/delete_message.py
telegrambots/wrapper/types/methods/delete_my_commands.py
telegrambots/wrapper/types/methods/delete_sticker_from_set.py
telegrambots/wrapper/types/methods/delete_webhook.py
telegrambots/wrapper/types/methods/edit_chat_invite_link.py
telegrambots/wrapper/types/methods/edit_message_caption.py
telegrambots-0.0.13rc0.dist-info/LICENSE
telegrambots-0.0.13rc0.dist-info/METADATA
telegrambots-0.0.13rc0.dist-info/WHEEL
telegrambots-0.0.13rc0.dist-info/top_level.txt
telegrambots-0.0.13rc0.dist-info/RECORD
