Metadata-Version: 2.1
Name: telegrambots
Version: 0.0.13rc0
Summary: A pure and modern python package for telegram bots.
Home-page: https://github.com/python-telegrambots/telegrambots
Author: immmdreza
Author-email: ir310022@gmail.com
Project-URL: Bug Tracker, https://github.com/immmdreza/python-telegrambots/issues
Classifier: Programming Language :: Python :: 3
Classifier: License :: OSI Approved :: MIT License
Classifier: Operating System :: OS Independent
Requires-Python: >=3.10
License-File: LICENSE
Requires-Dist: aiohttp (==3.8.1)
